MANIFEST.in
setup.py
cerberos/__init__.py
cerberos/admin.py
cerberos/decorators.py
cerberos/forms.py
cerberos/models.py
cerberos/settings.py
cerberos/tests.py
cerberos/urls.py
cerberos/views.py
cerberos.egg-info/PKG-INFO
cerberos.egg-info/SOURCES.txt
cerberos.egg-info/dependency_links.txt
cerberos.egg-info/top_level.txt
cerberos/locale/es/LC_MESSAGES/django.mo
cerberos/locale/es/LC_MESSAGES/django.po
cerberos/migrations/0001_initial.py
cerberos/migrations/0002_auto.py
cerberos/migrations/0003_auto__add_field_failedaccessattempt_locked.py
cerberos/migrations/0004_auto__chg_field_failedaccessattempt_http_accept.py
cerberos/migrations/0005_auto__add_field_failedaccessattempt_expired.py
cerberos/migrations/__init__.py
cerberos/templates/cerberos/user-locked.html
cerberos/templatetags/__init__.py
cerberos/templatetags/tt_cerberos.py
cerberos/tests/__init__.py
cerberos/tests/basic.py
docs/Makefile
docs/make.bat
docs/source/conf.py
docs/source/index.rst
testapp/__init__.py
testapp/manage.py
testapp/settings.py
testapp/urls.py
testapp/templates/base.html
testapp/templates/registration/login.html