Metadata-Version: 1.1
Name: cerberos
Version: 0.2.1
Summary: Cerberos is a django app that watches failed logins and block the user after N attempts.
Home-page: https://github.com/AdrianRibao/cerberos
Author: Adrián Ribao
Author-email: adrian@adrima.es
License: BSD
Platform: OS Independent
Classifier: Development Status :: 5 - Production/Stable
Classifier: Environment :: Web Environment
Classifier: Framework :: Django
Classifier: Intended Audience :: Developers
Classifier: License :: OSI Approved :: BSD License
Classifier: Operating System :: OS Independent
Classifier: Programming Language :: Python
Classifier: Topic :: Internet :: WWW/HTTP :: Dynamic Content
Classifier: Topic :: Software Development
Classifier: Topic :: Software Development :: Libraries :: Application Frameworks
